README.rst
setup.py
pycatastro/__init__.py
pycatastro.egg-info/PKG-INFO
pycatastro.egg-info/SOURCES.txt
pycatastro.egg-info/dependency_links.txt
pycatastro.egg-info/requires.txt
pycatastro.egg-info/top_level.txt