Metadata-Version: 1.0
Name: pycatastro
Version: 0.1.3
Summary: Module for Spanish Catastro
Home-page: https://github.com/gisce/pycatastro
Author: GISCE-TI, SL
Author-email: devel@gisce.net
License: GPLv3
Platform: UNKNOWN
